{
  "Data": {
    "slots": {
      "1": [
        "2021-04-09T17:15:00",
        "2021-04-09T17:30:00",
        "2021-04-09T18:45:00",
        "2021-04-09T19:00:00",
        "2021-04-09T19:15:00",
        "2021-04-09T19:30:00",
        "2021-04-09T19:45:00",
        "2021-04-10T10:15:00",
        "2021-04-10T12:45:00",
        "2021-04-10T14:30:00",
        "2021-04-10T16:30:00",
        "2021-04-10T16:45:00"
      ],
      "2": []
    }
  },
  "Status": "SUCCESS",
  "ErrCde": null,
  "ErrMsg": null,
  "ErrMsgDtl": null
}